sichuanlang/__init__.py
sichuanlang/__main__.py
sichuanlang/enable_import.py
sichuanlang/hanzi_util.py
sichuanlang/importer.py
sichuanlang/main.py
sichuanlang/parser.py
sichuanlang/parser_tplt.py
sichuanlang/demo/__init__.py
sichuanlang/demo/bead_sort.sichuan
sichuanlang/demo/binary_tree_sort.sichuan
sichuanlang/demo/bitonic_sort.sichuan
sichuanlang/demo/bubble_sort.sichuan
sichuanlang/demo/bucket_sort.sichuan
sichuanlang/demo/cocktail_shaker_sort.sichuan
sichuanlang/demo/comb_sort.sichuan
sichuanlang/demo/counting_sort.sichuan
sichuanlang/demo/cycle_sort.sichuan
sichuanlang/demo/factorial.sichuan
sichuanlang/demo/fibonacci_sequence.sichuan
sichuanlang/demo/gnome_sort.sichuan
sichuanlang/demo/heap_sort.sichuan
sichuanlang/demo/insertion_sort.sichuan
sichuanlang/demo/merge_sort.sichuan
sichuanlang/demo/odd_even_sort.sichuan
sichuanlang/demo/pancake_sort.sichuan
sichuanlang/demo/pigeonhole_sort.sichuan
sichuanlang/demo/proxmap_sort.sichuan
sichuanlang/demo/quick_sort.sichuan
sichuanlang/demo/radix_exchange_sort.sichuan
sichuanlang/demo/radix_sort.sichuan
sichuanlang/demo/selection_sort.sichuan
sichuanlang/demo/shell_sort.sichuan
sichuanlang/demo/slow_sort.sichuan
sichuanlang/demo/stooge_sort.sichuan
sichuanlang/demo/test.py
sichuanlang/demo/tim_sort.sichuan
sichuanlang/demo/tournament_sort.sichuan
SichuanLang-0.1.0.dist-info/LICENSE.txt
SichuanLang-0.1.0.dist-info/METADATA
SichuanLang-0.1.0.dist-info/WHEEL
SichuanLang-0.1.0.dist-info/entry_points.txt
SichuanLang-0.1.0.dist-info/top_level.txt
SichuanLang-0.1.0.dist-info/RECORD
